LICENSE
README.md
setup.py
putty_fib_py/__init__.py
putty_fib_py/version.py
putty_fib_py.egg-info/PKG-INFO
putty_fib_py.egg-info/SOURCES.txt
putty_fib_py.egg-info/dependency_links.txt
putty_fib_py.egg-info/entry_points.txt
putty_fib_py.egg-info/requires.txt
putty_fib_py.egg-info/top_level.txt
putty_fib_py/cmd/__init__.py
putty_fib_py/cmd/fib_numb.py
putty_fib_py/fib_calcs/__init__.py
putty_fib_py/fib_calcs/fib_number.py
putty_fib_py/fib_calcs/fib_numbers.py
tests/putty_fib_py/__init__.py
tests/putty_fib_py/fib_calcs/__init__.py
tests/putty_fib_py/fib_calcs/test_fib_number.py
tests/putty_fib_py/fib_calcs/test_fib_numbers.py