Metadata-Version: 2.4
Name: putty_fib_py
Version: 0.0.3
Summary: Calculates a Fibonacci number
Home-page: https://github.com/MikeForde/putty-fib-py
Author: Mike Forde
Author-email: mikforde@gmail.com
Classifier: Development Status :: 4 - Beta
Classifier: Programming Language :: Python :: 3
Classifier: Operating System :: OS Independent
Requires-Python: >=3
License-File: LICENSE
Requires-Dist: PyYAML>=4.1.2
Requires-Dist: dill>=0.2.8
Provides-Extra: server
Requires-Dist: Flask>=1.0.0; extra == "server"
Dynamic: author
Dynamic: author-email
Dynamic: classifier
Dynamic: description
Dynamic: description-content-type
Dynamic: home-page
Dynamic: license-file
Dynamic: provides-extra
Dynamic: requires-dist
Dynamic: requires-python
Dynamic: summary
